{
  "articleId": "1764135124532",
  "title": "息子がスーパーで「トマト」を床に落とした！ 店員さんの「大丈夫ですよ」の言葉に甘えたら、夫は「弁償したほうがいい」とのこと。安いものでも弁償は必要でしょうか？",
  "source": "ファイナンシャルフィールド",
  "date": "2025-11-25",
  "public": false,
  "text": "まず、法律的な観点から見ていきましょう。民法では、故意または過失によって他人の権利や法律上保護される利益を侵害した者は、これによって生じた損害を賠償する責任を負うと定められています。これを「不法行為責任」（民法第709条）といいます。\n \nスーパーで商品を落として破損させた場合、故意ではなくても過失（不注意）があれば、商品の所有者であるスーパーに対して損害賠償責任が発生する可能性があります。\n \nトマトであれば商品価値が失われた分、つまり販売価格相当額が損害額となるでしょう。したがって、法律的には弁償する義務が生じることになります。\n \nでは、商品を落としたのが小さな子どもだった場合はどうでしょうか。\n \n民法では、未成年者が他人に損害を加えた場合において、自己の行為の責任を弁識するに足りる知能を備えていなかったときは、その行為について賠償の責任を負わないと規定されています（民法第712条）。一般的に、12歳前後までの子どもは責任能力がないとされることが多いです。\n \nしかし、子ども本人に責任能力がない場合でも、その子どもを監督する法定の義務を負う者、つまり親権者である親が、子どもが第三者に加えた損害を賠償する責任を負うことになります。これを監督義務者責任（民法第714条）といいます。\n \nただし、監督義務者がその義務を怠らなかったとき、または義務を怠らなくても損害が生じたであろうときは、この限りではないとされています。\n \nこのように、法律的には弁償責任が発生する可能性がありますが、実際の店舗対応はどうでしょうか。\n \n多くのスーパーマーケットでは、お客が誤って商品を落としたり破損させたりした場合でも、弁償を求めないことが一般的です。これには以下のような理由があります。\n \nまず、商品の破損は店舗運営において一定程度想定される損失であり、多くの店舗では商品にかかる保険に加入しているため、個別のお客に弁償を求める必要性が低いという点が挙げられます。\n \nまた、たとえ数百円の商品を弁償してもらったとしても、そのことでお客が不快な思いをして二度と来店しなくなれば、長期的には店舗にとって大きな損失となります。\n \n弁償を求めないことで「親切に対応してくれる店」という印象を持ってもらい、リピーターになってもらうほうが、むしろ店舗の利益につながるという考え方です。\n \nそれでは、実際に子どもが商品を落としてしまった場合、どのように対応するのが適切でしょうか。まず大切なのは、すぐに店員に声をかけることです。黙ってその場を立ち去ることは避けましょう。\n \n店員が「こちらで処理します」と言ってくれた場合は、その言葉に甘えても問題ありません。ただし、申し訳ない気持ちを伝えることは大切です。\n \n一方、店員から弁償を求められた場合は、法律的には支払う義務がありますので、応じるのが適切でしょう。ただし、高額な請求や不当な要求と感じた場合は、一度冷静に確認することも必要です。\n \nまた、日頃から子どもに「店内を走り回らない」「商品は大切に扱う」などの基本的なマナーを教えておくことも、大切でしょう。\n \n仮に弁償する場合、トマト1個であれば数百円程度でしょう。しかし、高価な商品を破損させてしまった場合は、それなりの金額になる可能性があります。\n \nこのようなリスクに備えて、個人賠償責任保険に加入しておくことも1つの方法です。個人賠償責任保険は、日常生活で他人にけがをさせたり、他人のものを壊したりして法律上の損害賠償責任を負った場合に補償される保険です。\n \n多くの場合、自動車保険や火災保険の特約として月額数百円程度で付帯できます。子どもがいる家庭では、加入を検討する価値があるでしょう。年間で数千円の保険料を支払うことで、万一のときに数万円から数億円の賠償責任に備えることができます。\n \nスーパーで子どもが商品を落としてしまった場合、法律的には弁償責任が発生する可能性がありますが、実際の店舗では多くの場合、弁償を求められることはありません。\n \nただし、これは店舗側の善意によるものですので、商品を落としてしまったら必ず店員に声をかけ、謝罪することが大切です。日頃から子どもに買い物のマナーを教えることも、親の監督義務として重要でしょう。",
  "sentences": [
    {
      "id": "s1",
      "text": "まず、法律的な観点から見ていきましょう。",
      "type": "opinion",
      "confidence": 0.7,
      "predictionId": null
    },
    {
      "id": "s2",
      "text": "民法では、故意または過失によって他人の権利や法律上保護される利益を侵害した者は、これによって生じた損害を賠償する責任を負うと定められています。",
      "type": "fact",
      "confidence": 1,
      "predictionId": null
    },
    {
      "id": "s3",
      "text": "これを「不法行為責任」（民法第709条）といいます。",
      "type": "fact",
      "confidence": 1,
      "predictionId": null
    },
    {
      "id": "s4",
      "text": "スーパーで商品を落として破損させた場合、故意ではなくても過失（不注意）があれば、商品の所有者であるスーパーに対して損害賠償責任が発生する可能性があります。",
      "type": "prediction",
      "confidence": 0.9,
      "predictionId": "p1"
    },
    {
      "id": "s5",
      "text": "トマトであれば商品価値が失われた分、つまり販売価格相当額が損害額となるでしょう。",
      "type": "prediction",
      "confidence": 0.8,
      "predictionId": "p2"
    },
    {
      "id": "s6",
      "text": "したがって、法律的には弁償する義務が生じることになります。",
      "type": "prediction",
      "confidence": 0.9,
      "predictionId": "p3"
    },
    {
      "id": "s7",
      "text": "では、商品を落としたのが小さな子どもだった場合はどうでしょうか。",
      "type": "opinion",
      "confidence": 0.7,
      "predictionId": null
    },
    {
      "id": "s8",
      "text": "民法では、未成年者が他人に損害を加えた場合において、自己の行為の責任を弁識するに足りる知能を備えていなかったときは、その行為について賠償の責任を負わないと規定されています（民法第712条）。",
      "type": "fact",
      "confidence": 1,
      "predictionId": null
    },
    {
      "id": "s9",
      "text": "一般的に、12歳前後までの子どもは責任能力がないとされることが多いです。",
      "type": "fact",
      "confidence": 1,
      "predictionId": null
    },
    {
      "id": "s10",
      "text": "しかし、子ども本人に責任能力がない場合でも、その子どもを監督する法定の義務を負う者、つまり親権者である親が、子どもが第三者に加えた損害を賠償する責任を負うことになります。",
      "type": "fact",
      "confidence": 1,
      "predictionId": null
    },
    {
      "id": "s11",
      "text": "これを監督義務者責任（民法第714条）といいます。",
      "type": "fact",
      "confidence": 1,
      "predictionId": null
    },
    {
      "id": "s12",
      "text": "ただし、監督義務者がその義務を怠らなかったとき、または義務を怠らなくても損害が生じたであろうときは、この限りではないとされています。",
      "type": "fact",
      "confidence": 1,
      "predictionId": null
    },
    {
      "id": "s13",
      "text": "このように、法律的には弁償責任が発生する可能性がありますが、実際の店舗対応はどうでしょうか。",
      "type": "prediction",
      "confidence": 0.6,
      "predictionId": "p4"
    },
    {
      "id": "s14",
      "text": "多くのスーパーマーケットでは、お客が誤って商品を落としたり破損させたりした場合でも、弁償を求めないことが一般的です。",
      "type": "fact",
      "confidence": 1,
      "predictionId": null
    },
    {
      "id": "s15",
      "text": "これには以下のような理由があります。",
      "type": "opinion",
      "confidence": 0.7,
      "predictionId": null
    },
    {
      "id": "s16",
      "text": "まず、商品の破損は店舗運営において一定程度想定される損失であり、多くの店舗では商品にかかる保険に加入しているため、個別のお客に弁償を求める必要性が低いという点が挙げられます。",
      "type": "fact",
      "confidence": 1,
      "predictionId": null
    },
    {
      "id": "s17",
      "text": "また、たとえ数百円の商品を弁償してもらったとしても、そのことでお客が不快な思いをして二度と来店しなくなれば、長期的には店舗にとって大きな損失となります。",
      "type": "prediction",
      "confidence": 0.8,
      "predictionId": "p5"
    },
    {
      "id": "s18",
      "text": "弁償を求めないことで「親切に対応してくれる店」という印象を持ってもらい、リピーターになってもらうほうが、むしろ店舗の利益につながるという考え方です。",
      "type": "opinion",
      "confidence": 0.8,
      "predictionId": null
    },
    {
      "id": "s19",
      "text": "それでは、実際に子どもが商品を落としてしまった場合、どのように対応するのが適切でしょうか。",
      "type": "opinion",
      "confidence": 0.7,
      "predictionId": null
    },
    {
      "id": "s20",
      "text": "まず大切なのは、すぐに店員に声をかけることです。",
      "type": "opinion",
      "confidence": 0.8,
      "predictionId": null
    },
    {
      "id": "s21",
      "text": "黙ってその場を立ち去ることは避けましょう。",
      "type": "opinion",
      "confidence": 0.8,
      "predictionId": null
    },
    {
      "id": "s22",
      "text": "店員が「こちらで処理します」と言ってくれた場合は、その言葉に甘えても問題ありません。",
      "type": "opinion",
      "confidence": 0.9,
      "predictionId": null
    },
    {
      "id": "s23",
      "text": "ただし、申し訳ない気持ちを伝えることは大切です。",
      "type": "opinion",
      "confidence": 0.9,
      "predictionId": null
    },
    {
      "id": "s24",
      "text": "一方、店員から弁償を求められた場合は、法律的には支払う義務がありますので、応じるのが適切でしょう。",
      "type": "fact",
      "confidence": 1,
      "predictionId": null
    },
    {
      "id": "s25",
      "text": "ただし、高額な請求や不当な要求と感じた場合は、一度冷静に確認することも必要です。",
      "type": "opinion",
      "confidence": 0.8,
      "predictionId": null
    },
    {
      "id": "s26",
      "text": "また、日頃から子どもに「店内を走り回らない」「商品は大切に扱う」などの基本的なマナーを教えておくことも、大切でしょう。",
      "type": "opinion",
      "confidence": 0.8,
      "predictionId": null
    },
    {
      "id": "s27",
      "text": "仮に弁償する場合、トマト1個であれば数百円程度でしょう。",
      "type": "prediction",
      "confidence": 0.8,
      "predictionId": "p6"
    },
    {
      "id": "s28",
      "text": "しかし、高価な商品を破損させてしまった場合は、それなりの金額になる可能性があります。",
      "type": "prediction",
      "confidence": 0.8,
      "predictionId": "p7"
    },
    {
      "id": "s29",
      "text": "このようなリスクに備えて、個人賠償責任保険に加入しておくことも1つの方法です。",
      "type": "opinion",
      "confidence": 0.8,
      "predictionId": null
    },
    {
      "id": "s30",
      "text": "個人賠償責任保険は、日常生活で他人にけがをさせたり、他人のものを壊したりして法律上の損害賠償責任を負った場合に補償される保険です。",
      "type": "fact",
      "confidence": 1,
      "predictionId": null
    },
    {
      "id": "s31",
      "text": "多くの場合、自動車保険や火災保険の特約として月額数百円程度で付帯できます。",
      "type": "fact",
      "confidence": 1,
      "predictionId": null
    },
    {
      "id": "s32",
      "text": "子どもがいる家庭では、加入を検討する価値があるでしょう。",
      "type": "opinion",
      "confidence": 0.8,
      "predictionId": null
    },
    {
      "id": "s33",
      "text": "年間で数千円の保険料を支払うことで、万一のときに数万円から数億円の賠償責任に備えることができます。",
      "type": "prediction",
      "confidence": 0.8,
      "predictionId": "p8"
    },
    {
      "id": "s34",
      "text": "スーパーで子どもが商品を落としてしまった場合、法律的には弁償責任が発生する可能性がありますが、実際の店舗では多くの場合、弁償を求められることはありません。",
      "type": "prediction",
      "confidence": 0.9,
      "predictionId": "p9"
    },
    {
      "id": "s35",
      "text": "ただし、これは店舗側の善意によるものですので、商品を落としてしまったら必ず店員に声をかけ、謝罪することが大切です。",
      "type": "opinion",
      "confidence": 0.9,
      "predictionId": null
    },
    {
      "id": "s36",
      "text": "日頃から子どもに買い物のマナーを教えることも、親の監督義務として重要でしょう。",
      "type": "opinion",
      "confidence": 0.9,
      "predictionId": null
    }
  ],
  "summary": [
    "民法上では、過失によってスーパーの商品を破損した場合、弁償責任が生じることがある。",
    "小さな子どもが商品を壊した場合は原則として親が監督義務者として責任を負う。",
    "多くのスーパーマーケットでは実際には弁償を求めないことが一般的だが、店員に必ず声をかけて謝罪すべき。",
    "賠償リスクに備え、個人賠償責任保険の加入も有効とされる。",
    "実際には店舗の善意で弁償が免除されることが多いが、求められた場合は法的に支払う必要がある。"
  ],
  "futureTree": "Root → p1 → p2 → p3 → p4 → p5 → p6 → p7 → p8 → p9"
}